borgmatic/__init__.py
borgmatic/execute.py
borgmatic/logger.py
borgmatic/signals.py
borgmatic/verbosity.py
borgmatic/actions/__init__.py
borgmatic/actions/arguments.py
borgmatic/actions/borg.py
borgmatic/actions/break_lock.py
borgmatic/actions/change_passphrase.py
borgmatic/actions/check.py
borgmatic/actions/compact.py
borgmatic/actions/create.py
borgmatic/actions/delete.py
borgmatic/actions/export_key.py
borgmatic/actions/export_tar.py
borgmatic/actions/extract.py
borgmatic/actions/import_key.py
borgmatic/actions/info.py
borgmatic/actions/json.py
borgmatic/actions/list.py
borgmatic/actions/mount.py
borgmatic/actions/pattern.py
borgmatic/actions/prune.py
borgmatic/actions/recreate.py
borgmatic/actions/repo_create.py
borgmatic/actions/repo_delete.py
borgmatic/actions/repo_info.py
borgmatic/actions/repo_list.py
borgmatic/actions/restore.py
borgmatic/actions/transfer.py
borgmatic/actions/config/__init__.py
borgmatic/actions/config/bootstrap.py
borgmatic/actions/config/generate.py
borgmatic/actions/config/validate.py
borgmatic/borg/__init__.py
borgmatic/borg/borg.py
borgmatic/borg/break_lock.py
borgmatic/borg/change_passphrase.py
borgmatic/borg/check.py
borgmatic/borg/compact.py
borgmatic/borg/create.py
borgmatic/borg/delete.py
borgmatic/borg/environment.py
borgmatic/borg/export_key.py
borgmatic/borg/export_tar.py
borgmatic/borg/extract.py
borgmatic/borg/feature.py
borgmatic/borg/flags.py
borgmatic/borg/import_key.py
borgmatic/borg/info.py
borgmatic/borg/list.py
borgmatic/borg/mount.py
borgmatic/borg/passcommand.py
borgmatic/borg/pattern.py
borgmatic/borg/prune.py
borgmatic/borg/recreate.py
borgmatic/borg/rename.py
borgmatic/borg/repo_create.py
borgmatic/borg/repo_delete.py
borgmatic/borg/repo_info.py
borgmatic/borg/repo_list.py
borgmatic/borg/state.py
borgmatic/borg/transfer.py
borgmatic/borg/umount.py
borgmatic/borg/version.py
borgmatic/commands/__init__.py
borgmatic/commands/arguments.py
borgmatic/commands/borgmatic.py
borgmatic/commands/generate_config.py
borgmatic-2.0.13.dist-info/licenses/AUTHORS
borgmatic-2.0.13.dist-info/licenses/LICENSE
borgmatic-2.0.13.dist-info/METADATA
borgmatic-2.0.13.dist-info/WHEEL
borgmatic-2.0.13.dist-info/entry_points.txt
borgmatic-2.0.13.dist-info/top_level.txt
borgmatic-2.0.13.dist-info/RECORD
