Metadata-Version: 2.4
Name: borgmatic
Version: 2.0.13
Summary: Simple, configuration-driven backup software for servers and workstations
Author-email: Dan Helfman <witten@torsion.org>
Project-URL: Homepage, https://torsion.org/borgmatic
Classifier: Development Status :: 5 - Production/Stable
Classifier: Environment :: Console
Classifier: Intended Audience :: System Administrators
Classifier: License :: OSI Approved :: GNU General Public License v3 (GPLv3)
Classifier: Programming Language :: Python
Classifier: Topic :: Security :: Cryptography
Classifier: Topic :: System :: Archiving :: Backup
Requires-Python: >=3.9
License-File: LICENSE
License-File: AUTHORS
Requires-Dist: jsonschema
Requires-Dist: packaging
Requires-Dist: requests
Requires-Dist: ruamel.yaml>0.15.0
Provides-Extra: apprise
Requires-Dist: apprise; extra == "apprise"
Dynamic: license-file
